aws_glue_interactive_sessions_kernel/__init__.py
aws_glue_interactive_sessions_kernel/glue_kernel.py
aws_glue_interactive_sessions_kernel/glue_kernel_base/BaseKernel.py
aws_glue_interactive_sessions_kernel/glue_kernel_base/__init__.py
aws_glue_interactive_sessions_kernel/glue_kernel_configs/AWSFileConfigRetriever.py
aws_glue_interactive_sessions_kernel/glue_kernel_configs/ConfigRetriever.py
aws_glue_interactive_sessions_kernel/glue_kernel_configs/DefaultConfigRetriever.py
aws_glue_interactive_sessions_kernel/glue_kernel_configs/GlueConfigManager.py
aws_glue_interactive_sessions_kernel/glue_kernel_configs/OverriddenConfigRetriever.py
aws_glue_interactive_sessions_kernel/glue_kernel_configs/SystemEnvConfigRetriever.py
aws_glue_interactive_sessions_kernel/glue_kernel_configs/__init__.py
aws_glue_interactive_sessions_kernel/glue_kernel_configs/config.py
aws_glue_interactive_sessions_kernel/glue_kernel_utils/GlueSessionsConstants.py
aws_glue_interactive_sessions_kernel/glue_kernel_utils/KernelGateway.py
aws_glue_interactive_sessions_kernel/glue_kernel_utils/KernelMagics.py
aws_glue_interactive_sessions_kernel/glue_kernel_utils/ValidationUtils.py
aws_glue_interactive_sessions_kernel/glue_kernel_utils/__init__.py
aws_glue_interactive_sessions_kernel/glue_pyspark/GlueKernel.py
aws_glue_interactive_sessions_kernel/glue_pyspark/__init__.py
aws_glue_interactive_sessions_kernel/glue_pyspark/kernel.json
aws_glue_interactive_sessions_kernel/glue_pyspark/logo-128x128.png
aws_glue_interactive_sessions_kernel/glue_pyspark/logo-32x32.png
aws_glue_interactive_sessions_kernel/glue_pyspark/logo-64x64.png
aws_glue_interactive_sessions_kernel/glue_pyspark/glue/2017-03-31/service-2.json
aws_glue_interactive_sessions_kernel/glue_spark/GlueKernel.py
aws_glue_interactive_sessions_kernel/glue_spark/__init__.py
aws_glue_interactive_sessions_kernel/glue_spark/kernel.json
aws_glue_interactive_sessions_kernel/glue_spark/logo-128x128.png
aws_glue_sessions-1.0.9.dist-info/LICENSE
aws_glue_sessions-1.0.9.dist-info/METADATA
aws_glue_sessions-1.0.9.dist-info/WHEEL
aws_glue_sessions-1.0.9.dist-info/entry_points.txt
aws_glue_sessions-1.0.9.dist-info/top_level.txt
aws_glue_sessions-1.0.9.dist-info/RECORD
